README.md
setup.py
web_parsers/__init__.py
web_parsers/items.py
web_parsers.egg-info/PKG-INFO
web_parsers.egg-info/SOURCES.txt
web_parsers.egg-info/dependency_links.txt
web_parsers.egg-info/requires.txt
web_parsers.egg-info/top_level.txt
web_parsers/extractors/__init__.py
web_parsers/extractors/base.py
web_parsers/extractors/python.py
web_parsers/extractors/html/__init__.py
web_parsers/extractors/html/content.py
web_parsers/extractors/html/images.py
web_parsers/extractors/html/links.py
web_parsers/extractors/xml/__init__.py
web_parsers/extractors/xml/content.py
web_parsers/fields/__init__.py
web_parsers/fields/list.py
web_parsers/fields/single.py
web_parsers/manifest/__init__.py
web_parsers/manifest/common.py
web_parsers/manifest/items.py
web_parsers/manifest/alpha/__init__.py
web_parsers/manifest/alpha/html.py
web_parsers/manifest/alpha/xml.py
web_parsers/parsers/__init__.py
web_parsers/parsers/base.py
web_parsers/parsers/html.py
web_parsers/parsers/python.py
web_parsers/parsers/xml.py
web_parsers/utils/__init__.py
web_parsers/utils/exceptions.py
web_parsers/utils/other.py
web_parsers/utils/selectors.py
web_parsers/utils/url.py
web_parsers/utils/validators.py
web_parsers/utils/xml.py